{
    "include": [
        "src",
        "src/visualization"
    ],
    "exclude": [
        "**/node_modules",
        "**/__pycache__",
        "src/tests"
    ],
    "ignore": [
        "src/tests/test_*.py"
    ],
    "defineConstant": {
        "DEBUG": true
    },
    "typeCheckingMode": "basic",
    "useLibraryCodeForTypes": true,
    "reportMissingImports": true,
    "reportMissingTypeStubs": false,
    "pythonVersion": "3.8",
    "strictListInference": true,
    "strictDictionaryInference": true,
    "strictParameterNullChecking": true,
    "reportOptionalSubscript": "warning",
    "reportOptionalMemberAccess": "warning",
    "reportOptionalCall": "warning",
    "reportOptionalIterable": "warning",
    "reportOptionalContextManager": "warning",
    "reportOptionalOperand": "warning"
}